odoo8_addon_base_partner_merge-8.0.1.0.0.99.dev4-py3.8-nspkg.pth
odoo_addons/base_partner_merge/README.rst
odoo_addons/base_partner_merge/__init__.py
odoo_addons/base_partner_merge/__openerp__.py
odoo_addons/base_partner_merge/hooks.py
odoo_addons/base_partner_merge/validate_email.py
odoo_addons/base_partner_merge/i18n/base_partner_merge.pot
odoo_addons/base_partner_merge/i18n/de.po
odoo_addons/base_partner_merge/i18n/es.po
odoo_addons/base_partner_merge/i18n/eu.po
odoo_addons/base_partner_merge/i18n/fi.po
odoo_addons/base_partner_merge/i18n/it.po
odoo_addons/base_partner_merge/i18n/nl.po
odoo_addons/base_partner_merge/i18n/pt_BR.po
odoo_addons/base_partner_merge/i18n/sl.po
odoo_addons/base_partner_merge/models/__init__.py
odoo_addons/base_partner_merge/models/base_partner_merge.py
odoo_addons/base_partner_merge/models/base_partner_merge_automatic_wizard.py
odoo_addons/base_partner_merge/models/res_partner.py
odoo_addons/base_partner_merge/security/ir.model.access.csv
odoo_addons/base_partner_merge/static/description/icon.png
odoo_addons/base_partner_merge/tests/__init__.py
odoo_addons/base_partner_merge/tests/test_merge.py
odoo_addons/base_partner_merge/views/base_partner_merge.xml
odoo8_addon_base_partner_merge-8.0.1.0.0.99.dev4.dist-info/METADATA
odoo8_addon_base_partner_merge-8.0.1.0.0.99.dev4.dist-info/WHEEL
odoo8_addon_base_partner_merge-8.0.1.0.0.99.dev4.dist-info/namespace_packages.txt
odoo8_addon_base_partner_merge-8.0.1.0.0.99.dev4.dist-info/top_level.txt
odoo8_addon_base_partner_merge-8.0.1.0.0.99.dev4.dist-info/RECORD
